{
  "_fv": 39,
  "_type": "recipe",
  "definition": {
    "recipeType": "Crafting",
    "xpReward": 0.0,
    "cookingTime": 200,
    "recipeRetstackSize": 1,
    "group": "",
    "recipeShapeless": false,
    "recipeSlots": [
      {
        "value": "CUSTOM:Yuanshi"
      },
      {
        "value": "CUSTOM:Ranyuanduanpian"
      },
      {
        "value": "CUSTOM:Yuanshi"
      },
      {
        "value": "CUSTOM:Ranyuanduanpian"
      },
      {
        "value": "Items.NETHERITE_SCRAP"
      },
      {
        "value": "CUSTOM:Ranyuanduanpian"
      },
      {
        "value": "CUSTOM:Yuanshi"
      },
      {
        "value": "CUSTOM:Ranyuanduanpian"
      },
      {
        "value": "CUSTOM:Yuanshi"
      }
    ],
    "recipeReturnStack": {
      "value": "CUSTOM:Ryhjsj"
    },
    "name": "ryhjsjpf",
    "namespace": "mod"
  }
}